fw_core_client/__init__.py
fw_core_client/client.py
fw_core_client/config.py
fw_core_client/py.typed
fw_core_client-1.1.2.dist-info/LICENSE
fw_core_client-1.1.2.dist-info/WHEEL
fw_core_client-1.1.2.dist-info/METADATA
fw_core_client-1.1.2.dist-info/RECORD
