Metadata-Version: 2.1
Name: fw-core-client
Version: 1.1.2
Summary: Flywheel Core HTTP API client
Home-page: https://gitlab.com/flywheel-io/tools/lib/fw-core-client
License: MIT
Keywords: Flywheel,API,Core,HTTP,client
Author: Flywheel
Author-email: support@flywheel.io
Requires-Python: >=3.7,<4.0
Classifier: License :: OSI Approved :: MIT License
Classifier: Programming Language :: Python :: 3
Classifier: Programming Language :: Python :: 3.10
Classifier: Programming Language :: Python :: 3.7
Classifier: Programming Language :: Python :: 3.8
Classifier: Programming Language :: Python :: 3.9
Classifier: Topic :: Software Development :: Libraries :: Python Modules
Requires-Dist: fw-http-client (>=1.0.4,<2.0.0)
Requires-Dist: fw-utils (>=3,<5)
Requires-Dist: importlib-metadata (>=4.8.2,<5.0.0); python_version < "3.8"
Requires-Dist: memoization (>=0,<1)
Requires-Dist: packaging (>=21.0,<22.0)
Requires-Dist: pydantic (>=1.6.1,<2.0.0)
Project-URL: Documentation, https://gitlab.com/flywheel-io/tools/lib/fw-core-client/-/blob/master/README.md
Project-URL: Repository, https://gitlab.com/flywheel-io/tools/lib/fw-core-client
